[
  {
    "id": "aceofair",
    "past": "Previously, Ace Of Air guided you toward intellect.",
    "present": "At this moment, Ace Of Air reflects intellect.",
    "future": "Soon, Ace Of Air ushers in intellect."
  },
  {
    "id": "aceofbone",
    "past": "Long ago, Ace Of Bone spoke of security.",
    "present": "Right now, it points to stability.",
    "future": "Looking ahead, expect resources."
  },
  {
    "id": "aceoffire",
    "past": "Previously, Ace Of Fire guided you toward energy.",
    "present": "At this moment, Ace Of Fire reflects passion.",
    "future": "Soon, Ace Of Fire ushers in impulse."
  },
  {
    "id": "aceofwater",
    "past": "In the past, Ace Of Water highlighted flow.",
    "present": "Right now, it points to emotion.",
    "future": "In time, Ace Of Water will reveal healing."
  },
  {
    "id": "bonereader",
    "past": "In the past, Bone Reader highlighted foundation.",
    "present": "Currently, Bone Reader encourages stability.",
    "future": "In time, Bone Reader will reveal stability."
  },
  {
    "id": "drumawakens",
    "past": "Long ago, Drum Awakens spoke of mystery.",
    "present": "At this moment, Drum Awakens reflects mystery.",
    "future": "Looking ahead, expect transformation."
  },
  {
    "id": "fireeater",
    "past": "In the past, FIRE EATER highlighted energy.",
    "present": "Right now, it points to passion.",
    "future": "Soon, FIRE EATER ushers in energy."
  },
  {
    "id": "firepit",
    "past": "Long ago, Fire Pit spoke of impulse.",
    "present": "Currently, Fire Pit encourages impulse.",
    "future": "In time, Fire Pit will reveal passion."
  },
  {
    "id": "fiveofair",
    "past": "In the past, Five Of Air highlighted intellect.",
    "present": "At this moment, Five Of Air reflects clarity.",
    "future": "Soon, Five Of Air ushers in intellect."
  },
  {
    "id": "fiveofbone",
    "past": "Previously, Five Of Bone guided you toward stability.",
    "present": "Currently, Five Of Bone encourages security.",
    "future": "Soon, Five Of Bone ushers in security."
  },
  {
    "id": "fiveoffire",
    "past": "In the past, Five Of Fire highlighted impulse.",
    "present": "Right now, it points to passion.",
    "future": "Soon, Five Of Fire ushers in impulse."
  },
  {
    "id": "fiveofwater",
    "past": "Previously, Five Of Water guided you toward flow.",
    "present": "Currently, Five Of Water encourages flow.",
    "future": "In time, Five Of Water will reveal intuition."
  },
  {
    "id": "fourofbone",
    "past": "Previously, Four Of Bone guided you toward stability.",
    "present": "Currently, Four Of Bone encourages foundation.",
    "future": "In time, Four Of Bone will reveal stability."
  },
  {
    "id": "fouroffire",
    "past": "In the past, Four Of Fire highlighted courage.",
    "present": "Right now, it points to passion.",
    "future": "In time, Four Of Fire will reveal courage."
  },
  {
    "id": "fourofwater",
    "past": "In the past, Fourofwater highlighted healing.",
    "present": "Currently, Fourofwater encourages flow.",
    "future": "Looking ahead, expect healing."
  },
  {
    "id": "kingofair",
    "past": "Previously, King Of Air guided you toward clarity.",
    "present": "Right now, it points to decision.",
    "future": "Looking ahead, expect decision."
  },
  {
    "id": "kingofbone",
    "past": "Long ago, King Of Bone spoke of security.",
    "present": "At this moment, King Of Bone reflects resources.",
    "future": "Looking ahead, expect stability."
  },
  {
    "id": "kingoffire",
    "past": "Long ago, King Of Fire spoke of courage.",
    "present": "Right now, it points to energy.",
    "future": "Soon, King Of Fire ushers in impulse."
  },
  {
    "id": "kingofwater",
    "past": "In the past, King Of Water highlighted emotion.",
    "present": "Currently, King Of Water encourages flow.",
    "future": "Soon, King Of Water ushers in intuition."
  },
  {
    "id": "magician",
    "past": "In the past, Magician highlighted power.",
    "present": "Currently, Magician encourages transformation.",
    "future": "Looking ahead, expect transformation."
  },
  {
    "id": "matriarch",
    "past": "Long ago, Matriarch spoke of change.",
    "present": "Right now, it points to mystery.",
    "future": "Looking ahead, expect power."
  },
  {
    "id": "moonwake",
    "past": "In the past, Moonwake highlighted insight.",
    "present": "At this moment, Moonwake reflects transformation.",
    "future": "In time, Moonwake will reveal transformation."
  },
  {
    "id": "pathfinders",
    "past": "Previously, Pathfinders guided you toward mystery.",
    "present": "Right now, it points to insight.",
    "future": "Looking ahead, expect insight."
  },
  {
    "id": "queenofair",
    "past": "Long ago, Queen Of Air spoke of clarity.",
    "present": "Currently, Queen Of Air encourages logic.",
    "future": "Soon, Queen Of Air ushers in intellect."
  },
  {
    "id": "queenofbone",
    "past": "In the past, Queen Of Bone highlighted stability.",
    "present": "Right now, it points to resources.",
    "future": "Soon, Queen Of Bone ushers in foundation."
  },
  {
    "id": "queenoffire",
    "past": "Long ago, Queen Of Fire spoke of energy.",
    "present": "Right now, it points to passion.",
    "future": "In time, Queen Of Fire will reveal energy."
  },
  {
    "id": "queenofwater",
    "past": "In the past, Queen Of Water highlighted healing.",
    "present": "Right now, it points to intuition.",
    "future": "In time, Queen Of Water will reveal healing."
  },
  {
    "id": "sevenofair",
    "past": "Previously, Seven Of Air guided you toward logic.",
    "present": "At this moment, Seven Of Air reflects clarity.",
    "future": "Looking ahead, expect decision."
  },
  {
    "id": "sevenofbone",
    "past": "Long ago, Seven Of Bone spoke of resources.",
    "present": "Currently, Seven Of Bone encourages stability.",
    "future": "Soon, Seven Of Bone ushers in foundation."
  },
  {
    "id": "sevenoffire",
    "past": "Previously, Seven Of Fire guided you toward energy.",
    "present": "Right now, it points to energy.",
    "future": "Soon, Seven Of Fire ushers in impulse."
  },
  {
    "id": "sevenofwater",
    "past": "Previously, Seven Of Water guided you toward intuition.",
    "present": "At this moment, Seven Of Water reflects flow.",
    "future": "Looking ahead, expect intuition."
  },
  {
    "id": "shadowspear",
    "past": "Long ago, Shadow Spear spoke of growth.",
    "present": "Currently, Shadow Spear encourages insight.",
    "future": "Looking ahead, expect power."
  },
  {
    "id": "sixofair",
    "past": "In the past, Six Of Air highlighted logic.",
    "present": "Currently, Six Of Air encourages decision.",
    "future": "Looking ahead, expect decision."
  },
  {
    "id": "sixofbone",
    "past": "Long ago, Six Of Bone spoke of security.",
    "present": "At this moment, Six Of Bone reflects stability.",
    "future": "Soon, Six Of Bone ushers in foundation."
  },
  {
    "id": "sixoffire",
    "past": "In the past, Six Of Fire highlighted passion.",
    "present": "At this moment, Six Of Fire reflects passion.",
    "future": "In time, Six Of Fire will reveal impulse."
  },
  {
    "id": "sixofwater",
    "past": "In the past, Six Of Water highlighted flow.",
    "present": "Currently, Six Of Water encourages emotion.",
    "future": "Looking ahead, expect healing."
  },
  {
    "id": "starcaller",
    "past": "Long ago, Starcaller spoke of change.",
    "present": "At this moment, Starcaller reflects growth.",
    "future": "Looking ahead, expect change."
  },
  {
    "id": "stonefall",
    "past": "In the past, Stone Fall highlighted growth.",
    "present": "Currently, Stone Fall encourages mystery.",
    "future": "Soon, Stone Fall ushers in growth."
  },
  {
    "id": "strength",
    "past": "Long ago, Strength spoke of power.",
    "present": "Currently, Strength encourages transformation.",
    "future": "In time, Strength will reveal growth."
  },
  {
    "id": "sunknight",
    "past": "Long ago, Sunknight spoke of change.",
    "present": "At this moment, Sunknight reflects transformation.",
    "future": "Looking ahead, expect mystery."
  },
  {
    "id": "suntribe",
    "past": "Previously, Suntribe guided you toward change.",
    "present": "At this moment, Suntribe reflects change.",
    "future": "Looking ahead, expect change."
  },
  {
    "id": "suspendedpath",
    "past": "In the past, Suspended Path highlighted insight.",
    "present": "Right now, it points to mystery.",
    "future": "In time, Suspended Path will reveal power."
  },
  {
    "id": "temperence",
    "past": "In the past, Temperence highlighted power.",
    "present": "At this moment, Temperence reflects change.",
    "future": "Soon, Temperence ushers in growth."
  },
  {
    "id": "theearthfather",
    "past": "Previously, The Earthfather guided you toward growth.",
    "present": "At this moment, The Earthfather reflects change.",
    "future": "Soon, The Earthfather ushers in power."
  },
  {
    "id": "theskydrum",
    "past": "Previously, The Sky Drum guided you toward growth.",
    "present": "At this moment, The Sky Drum reflects insight.",
    "future": "In time, The Sky Drum will reveal change."
  },
  {
    "id": "theweaver",
    "past": "In the past, The Weaver highlighted change.",
    "present": "At this moment, The Weaver reflects insight.",
    "future": "Looking ahead, expect growth."
  },
  {
    "id": "threeofair",
    "past": "Long ago, Three Of Air spoke of clarity.",
    "present": "Currently, Three Of Air encourages intellect.",
    "future": "Looking ahead, expect clarity."
  },
  {
    "id": "threeofbone",
    "past": "Long ago, Three Of Bone spoke of security.",
    "present": "At this moment, Three Of Bone reflects resources.",
    "future": "Soon, Three Of Bone ushers in foundation."
  },
  {
    "id": "threeoffire",
    "past": "In the past, Three Of Fire highlighted energy.",
    "present": "Currently, Three Of Fire encourages passion.",
    "future": "In time, Three Of Fire will reveal passion."
  },
  {
    "id": "threeofwater",
    "past": "Long ago, Three Of Water spoke of healing.",
    "present": "Right now, it points to healing.",
    "future": "In time, Three Of Water will reveal healing."
  },
  {
    "id": "timecave",
    "past": "Long ago, Time Cave spoke of growth.",
    "present": "Right now, it points to insight.",
    "future": "Looking ahead, expect growth."
  },
  {
    "id": "tracker",
    "past": "In the past, Tracker highlighted power.",
    "present": "Right now, it points to power.",
    "future": "Soon, Tracker ushers in power."
  },
  {
    "id": "twoofair",
    "past": "Previously, Two Of Air guided you toward clarity.",
    "present": "Right now, it points to clarity.",
    "future": "Looking ahead, expect decision."
  },
  {
    "id": "twooffire",
    "past": "Previously, Two Of Fire guided you toward passion.",
    "present": "Right now, it points to courage.",
    "future": "Looking ahead, expect passion."
  },
  {
    "id": "twoofwater",
    "past": "Previously, Two Of Water guided you toward intuition.",
    "present": "Currently, Two Of Water encourages intuition.",
    "future": "Looking ahead, expect healing."
  },
  {
    "id": "extra1",
    "past": "In the past, Extra Card 1 highlighted power.",
    "present": "Currently, Extra Card 1 encourages transformation.",
    "future": "Soon, Extra Card 1 ushers in insight."
  },
  {
    "id": "extra2",
    "past": "Long ago, Extra Card 2 spoke of change.",
    "present": "Right now, it points to mystery.",
    "future": "In time, Extra Card 2 will reveal insight."
  },
  {
    "id": "extra3",
    "past": "In the past, Extra Card 3 highlighted growth.",
    "present": "Currently, Extra Card 3 encourages insight.",
    "future": "Looking ahead, expect insight."
  },
  {
    "id": "extra4",
    "past": "Long ago, Extra Card 4 spoke of transformation.",
    "present": "At this moment, Extra Card 4 reflects transformation.",
    "future": "Soon, Extra Card 4 ushers in change."
  },
  {
    "id": "extra5",
    "past": "Long ago, Extra Card 5 spoke of transformation.",
    "present": "Right now, it points to insight.",
    "future": "Looking ahead, expect growth."
  },
  {
    "id": "extra6",
    "past": "Previously, Extra Card 6 guided you toward mystery.",
    "present": "At this moment, Extra Card 6 reflects insight.",
    "future": "In time, Extra Card 6 will reveal transformation."
  },
  {
    "id": "extra7",
    "past": "Previously, Extra Card 7 guided you toward growth.",
    "present": "Right now, it points to insight.",
    "future": "In time, Extra Card 7 will reveal transformation."
  },
  {
    "id": "extra8",
    "past": "In the past, Extra Card 8 highlighted change.",
    "present": "Right now, it points to power.",
    "future": "Soon, Extra Card 8 ushers in mystery."
  },
  {
    "id": "extra9",
    "past": "Long ago, Extra Card 9 spoke of insight.",
    "present": "At this moment, Extra Card 9 reflects mystery.",
    "future": "Looking ahead, expect power."
  },
  {
    "id": "extra10",
    "past": "In the past, Extra Card 10 highlighted mystery.",
    "present": "Currently, Extra Card 10 encourages change.",
    "future": "In time, Extra Card 10 will reveal power."
  },
  {
    "id": "extra11",
    "past": "Previously, Extra Card 11 guided you toward growth.",
    "present": "At this moment, Extra Card 11 reflects insight.",
    "future": "Soon, Extra Card 11 ushers in growth."
  }]